{
    "id": 10,
    "date": "2025-10-23",
    "title": "RDS 스냅샷 계정 이전",
    "level": "중",
    "time": "1시간",
    "price": "2만원",
    "image": "",
    "process": [
        {
            "step": 1,
            "title": "KMS 키 생성",
            "content": "대상 계정에서 RDS 스냅샷 암호화에 사용할 KMS 키를 생성합니다. 이 키는 스냅샷을 암호화하고 복호화하는 데 사용됩니다."
        },
        {
            "step": 2,
            "title": "원본 RDS 스냅샷 공유",
            "content": "원본 계정에서 대상 계정으로 RDS 스냅샷을 공유합니다. 스냅샷의 권한을 수정하여 대상 계정이 액세스할 수 있도록 설정합니다."
        },
        {
            "step": 3,
            "title": "복구 RDS 스냅샷 복구",
            "content": "대상 계정에서 공유된 RDS 스냅샷을 사용하여 새로운 RDS 인스턴스를 복구합니다."
        }
    ]
}