{
    "id": 11,
    "date": "2025-05-05",
    "title": "AWS EC2 스프링부트, 리액트 웹 서버 구축",
    "development": {
        "frontend": "React",
        "backend": "SpringBoot",
        "database": "MySQL",
        "linkage": null
    },
    "requirements": {
        "hosting": "AWS",
        "budget": 60000,
        "environment": "운영",
        "app_deploy": "자동",
        "security": "SSL, 방화벽",
        "performance": "업스케일링",
        "etc": null
    },
    "design": {
        "instance": "EC2",
        "network": "Public",
        "os": "Amazon Linux",
        "storage": "EBS, S3",
        "dns": "Route 53",
        "webserver": "Nginx",
        "database": "MySQL",
        "deploy": {
            "frontend": "React",
            "backend": "SpringBoot",
            "source": "Github",
            "build": "Github Actions",
            "deploy": "CodeDeploy"
        },
        "security": {
            "tools": "SSL (Let's Encrypt), WAF (ModSecurity)",
            "etc": null
        },
        "extension": {
            "loadbalancer": null,
            "autoscaling": null,
            "cdn": null
        },
        "software": null
    },
    "schedule": [
        {
            "no": 1,
            "category": "기본",
            "title": "아키텍처 설계",
            "working_day": 0.5
        },
        {
            "no": 2,
            "category": "배포",
            "title": "프론트 CI/CD",
            "working_day": 1
        },
        {
            "no": 3,
            "category": "배포",
            "title": "백엔드 CI/CD",
            "working_day": 1
        },
        {
            "no": 4,
            "category": "보안",
            "title": "보안 도구 설치",
            "working_day": 0.5
        },
        {
            "no": 5,
            "category": "테스트",
            "title": "통합 테스트",
            "working_day": 1
        },
        {
            "no": 6,
            "category": "완료",
            "title": "문서화 및 인계",
            "working_day": 0.5
        }
    ],
    "estimate": [
        {
            "no": 1,
            "work": "기본 아키텍처 설계",
            "supplyPrice": 60000,
            "quantity": 1,
            "sumPrice": 60000
        },
        {
            "no": 2,
            "work": "프론트 CI/CD",
            "supplyPrice": 80000,
            "quantity": 1,
            "sumPrice": 80000
        },
        {
            "no": 3,
            "work": "백엔드 CI/CD",
            "supplyPrice": 120000,
            "quantity": 1,
            "sumPrice": 120000
        },
        {
            "no": 4,
            "work": "보안 도구 설치",
            "supplyPrice": 60000,
            "quantity": 1,
            "sumPrice": 60000
        }
    ]
}